pythonflex/__init__.py
pythonflex/analysis.py
pythonflex/logging_config.py
pythonflex/plotting.py
pythonflex/preprocessing.py
pythonflex/utils.py
pythonflex/data/dataset/liver_cell_lines_500_genes.csv
pythonflex/data/dataset/melanoma_cell_lines_500_genes.csv
pythonflex/data/dataset/neuroblastoma_cell_lines_500_genes.csv
pythonflex/data/gold_standard/CORUM.parquet
pythonflex/data/gold_standard/GOBP.parquet
pythonflex/data/gold_standard/PATHWAY.parquet
pythonflex/data/gold_standard/corum.csv
pythonflex/data/gold_standard/gobp.csv
pythonflex/data/gold_standard/pathway.csv
pythonflex/examples/basic_usage.py
pythonflex/examples/dataset_filtering.py
pythonflex/examples/test.py
pythonflex-0.2.4.dist-info/METADATA
pythonflex-0.2.4.dist-info/WHEEL
pythonflex-0.2.4.dist-info/entry_points.txt
pythonflex-0.2.4.dist-info/RECORD
