Metadata-Version: 2.4
Name: pythonflex
Version: 0.2.4
Summary: pythonFLEX is a benchmarking toolkit for evaluating CRISPR screen results against biological gold standards. The toolkit computes gene-level and complex-level performance metrics, helping researchers systematically assess the biological relevance and resolution of their CRISPR screening data.
Author-email: Yasir Demirtaş <tyasird@hotmail.com>
Requires-Python: >=3.9
Requires-Dist: adjusttext
Requires-Dist: art
Requires-Dist: bitarray
Requires-Dist: emoji
Requires-Dist: importlib-resources
Requires-Dist: ipython
Requires-Dist: joblib
Requires-Dist: loguru
Requires-Dist: matplotlib
Requires-Dist: numba
Requires-Dist: numpy
Requires-Dist: pandas
Requires-Dist: pyarrow
Requires-Dist: python-slugify
Requires-Dist: scikit-learn
Requires-Dist: scipy
Requires-Dist: tqdm
